LICENSE
MANIFEST.in
README.rst
setup.py
examples/io/file.py
examples/plotting/plot_autobinning.py
examples/plotting/plot_bin_merging.py
examples/plotting/plot_hist.py
examples/plotting/plot_matplotlib_graph.py
examples/plotting/plot_matplotlib_hist.py
examples/plotting/plot_matplotlib_hist2d.py
examples/plotting/plot_overlay.py
examples/plotting/plot_style.py
examples/stats/plot_quantiles.py
examples/tree/chain.py
examples/tree/chain_overwrite.py
examples/tree/model.py
examples/tree/model_simple.py
examples/tree/ntuple.py
examples/tree/object_branch.py
examples/tree/overwrite.py
examples/tree/user_object.py
examples/tree/vararray.py
requirements/array.txt
requirements/matplotlib.txt
requirements/roosh.txt
requirements/stats.txt
requirements/tables.txt
rootpy/ROOT.py
rootpy/__init__.py
rootpy/base.py
rootpy/collection.py
rootpy/compiled.py
rootpy/context.py
rootpy/decorators.py
rootpy/defaults.py
rootpy/info.py
rootpy/matrix.py
rootpy/roosh.py
rootpy/root2hdf5.py
rootpy/stl.py
rootpy/userdata.py
rootpy/vector.py
rootpy.egg-info/PKG-INFO
rootpy.egg-info/SOURCES.txt
rootpy.egg-info/dependency_links.txt
rootpy.egg-info/entry_points.txt
rootpy.egg-info/requires.txt
rootpy.egg-info/top_level.txt
rootpy/etc/pdg_table.txt
rootpy/extern/__init__.py
rootpy/extern/argparse.py
rootpy/extern/close_variable.py
rootpy/extern/ordereddict.py
rootpy/extern/pyparsing.py
rootpy/extern/six.py
rootpy/extern/byteplay2/__init__.py
rootpy/extern/byteplay3/__init__.py
rootpy/extern/byteplay3/byteplay.py
rootpy/extern/byteplay3/wbyteplay.py
rootpy/extern/hep/__init__.py
rootpy/extern/hep/pdg.py
rootpy/extern/lockfile/__init__.py
rootpy/extern/lockfile/linklockfile.py
rootpy/extern/lockfile/mkdirlockfile.py
rootpy/extern/lockfile/pidlockfile.py
rootpy/extern/lockfile/sqlitelockfile.py
rootpy/extern/lockfile/symlinklockfile.py
rootpy/extern/progressbar/__init__.py
rootpy/extern/progressbar/widgets.py
rootpy/extern/shortuuid/__init__.py
rootpy/interactive/__init__.py
rootpy/interactive/canvas_events.py
rootpy/interactive/console.py
rootpy/interactive/notebook.py
rootpy/interactive/rootwait.py
rootpy/io/__init__.py
rootpy/io/file.py
rootpy/io/pickler.py
