Metadata-Version: 1.1
Name: rootpy
Version: 1.0.0
Summary: A pythonic layer on top of the ROOT framework's PyROOT bindings.
Home-page: http://rootpy.github.com/rootpy
Author: Noel Dawe
Author-email: noel@dawe.me
License: new BSD
Download-URL: http://pypi.python.org/packages/source/r/rootpy/rootpy-1.0.0.tar.gz
Platform: UNKNOWN
Classifier: Intended Audience :: Science/Research
Classifier: Intended Audience :: Developers
Classifier: Topic :: Software Development
Classifier: Topic :: Scientific/Engineering
Classifier: Topic :: Utilities
Classifier: Operating System :: POSIX
Classifier: Operating System :: Unix
Classifier: Operating System :: MacOS
Classifier: License :: OSI Approved :: BSD License
Classifier: Programming Language :: Python
Classifier: Programming Language :: Python :: 2
Classifier: Programming Language :: Python :: 3
Classifier: Development Status :: 4 - Beta
